setup.py
conifertools/__init__.py
conifertools/call.mpi.py
conifertools/conifertools.py
conifertools/hcluster.py
conifertools/mpi_submit.py
conifertools/mpi_wrapper.py
conifertools/plotting.py
conifertools/rpkm.py
conifertools.egg-info/PKG-INFO
conifertools.egg-info/SOURCES.txt
conifertools.egg-info/dependency_links.txt
conifertools.egg-info/not-zip-safe
conifertools.egg-info/top_level.txt