Metadata-Version: 1.1
Name: conifertools
Version: 0.1
Summary: A collection of helpful tools for use with CoNIFER
Home-page: http://github.com/nkrumm/conifer-tools
Author: Niklas Krumm
Author-email: nkrumm@gmail.com
License: UNKNOWN
Download-URL: https://github.com/nkrumm/conifer-tools/tarball/0.1
Platform: UNKNOWN
